udn_songbook/__init__.py
udn_songbook/book.py
udn_songbook/config.py
udn_songbook/defaults.toml
udn_songbook/filters.py
udn_songbook/py.typed
udn_songbook/renderer.py
udn_songbook/song.py
udn_songbook/utils.py
udn_songbook/stylesheets/landscape.css
udn_songbook/stylesheets/portrait.css
udn_songbook/stylesheets/responsive.css
udn_songbook/stylesheets/ukedown.css
udn_songbook/templates/base.html.j2
udn_songbook/templates/index.html.j2
udn_songbook/templates/song.html.j2
udn_songbook/tools/fromug.py
udn_songbook/tools/makesheet.py
udn_songbook/tools/parse_test.py
udn_songbook/tools/pdfbook.py
udn_songbook/tools/transpose.py
udn_songbook-1.5.0.dist-info/METADATA
udn_songbook-1.5.0.dist-info/WHEEL
udn_songbook-1.5.0.dist-info/entry_points.txt
udn_songbook-1.5.0.dist-info/licenses/LICENSE.txt
udn_songbook-1.5.0.dist-info/RECORD
