Metadata-Version: 2.4
Name: udn-songbook
Version: 1.5.0
Summary: songbook and songsheet management for songsheets in ukedown format
Project-URL: Repository, https://github.com/lanky/udn-songbook
Project-URL: Issues, https://github.com/lanky/udn-songbook/issues
Author-email: Stuart Sears <stuart@sjsears.com>
Maintainer-email: Stuart Sears <stuart@sjsears.com>
License-Expression: GPL-3.0-or-later
License-File: LICENSE.txt
Classifier: Development Status :: 4 - Beta
Classifier: Intended Audience :: Developers
Classifier: Programming Language :: Python :: 3
Classifier: Programming Language :: Python :: 3.10
Classifier: Programming Language :: Python :: 3.11
Classifier: Programming Language :: Python :: 3.12
Classifier: Programming Language :: Python :: 3.13
Requires-Python: >=3.12
Requires-Dist: beautifulsoup4>=4.13.3
Requires-Dist: dynaconf>=3.2.10
Requires-Dist: jinja2>=3.1.6
Requires-Dist: jmespath>=1.0.1
Requires-Dist: loguru>=0.7.3
Requires-Dist: lxml>=5.3.1
Requires-Dist: markdown>=3.7
Requires-Dist: more-itertools>=10.6.0
Requires-Dist: platformdirs>=4.3.6
Requires-Dist: pychord>=1.2.2
Requires-Dist: pyyaml>=6.0.2
Requires-Dist: requests>=2.32.4
Requires-Dist: tqdm>=4.67.1
Requires-Dist: ukedown>=2.2.2
Requires-Dist: weasyprint>=65.0
